pywingame/__init__.py
pywingame/element.py
pywingame/event.py
pywingame/image.py
pywingame/widget.py
pywingame/window.py
pywingame-0.0.1.dist-info/METADATA
pywingame-0.0.1.dist-info/WHEEL
pywingame-0.0.1.dist-info/top_level.txt
pywingame-0.0.1.dist-info/RECORD
