Metadata-Version: 2.1
Name: pywingame
Version: 0.0.1
Summary: A game engine based on pygame. It allows you to make your own games.
Author: JacksonLin (JacksonLin)
Author-email: jacksonlam.macau@outlook.com
Keywords: python,game,game engine
Classifier: Development Status :: 1 - Planning
Classifier: Intended Audience :: Developers
Classifier: Programming Language :: Python :: 3
Classifier: Operating System :: Microsoft :: Windows
Requires-Dist: pygame
Requires-Dist: clipboard
